LICENSE
README.md
setup.py
NumberScript/__init__.py
NumberScript/interpreter.py
NumberScript/main.py
NumberScript/nspm.py
NumberScript.egg-info/PKG-INFO
NumberScript.egg-info/SOURCES.txt
NumberScript.egg-info/dependency_links.txt
NumberScript.egg-info/entry_points.txt
NumberScript.egg-info/top_level.txt