Metadata-Version: 2.1
Name: NumberScript
Version: 1.13.5
Summary: possibly the world's most simplest and restricted language.
Author: Sasen Perera
License: MIT
Classifier: Programming Language :: Python :: 3
Classifier: License :: OSI Approved :: MIT License
Classifier: Operating System :: OS Independent
Requires-Python: >=3.6
License-File: LICENSE
